doma/__init__.py
doma/apps.py
doma/migrations/0001_initial.py
doma/migrations/0002_alter_document_file.py
doma/migrations/0003_alter_document_preview.py
doma/migrations/0004_alter_document_replaces.py
doma/migrations/__init__.py
doma/models.py
doma/settings.py
doma/signals.py
django_doma-0.2.2.dist-info/WHEEL
django_doma-0.2.2.dist-info/METADATA
django_doma-0.2.2.dist-info/RECORD
