Metadata-Version: 2.1
Name: django-doma
Version: 0.2.2
Summary: Simple Document Management for Django
Home-page: https://github.com/olf42/django-doma
License: GPL-3.0
Author: Florian Rämisch
Author-email: olf@subsignal.org
Requires-Python: >=3.6,<4.0
Classifier: License :: OSI Approved :: GNU General Public License v3 (GPLv3)
Classifier: Programming Language :: Python :: 3
Classifier: Programming Language :: Python :: 3.6
Classifier: Programming Language :: Python :: 3.7
Classifier: Programming Language :: Python :: 3.8
Classifier: Programming Language :: Python :: 3.9
Requires-Dist: Django (>=3.2,<4.0)
Requires-Dist: Pillow (>=8.2.0,<9.0.0)
Requires-Dist: freezegun (>=1.1.0,<2.0.0)
Requires-Dist: pdf2image (>=1.14.0,<2.0.0)
Project-URL: Repository, https://github.com/olf42/django-doma
